cdk_eks_karpenter/__init__.py
cdk_eks_karpenter/py.typed
cdk_eks_karpenter/_jsii/__init__.py
cdk_eks_karpenter/_jsii/cdk-eks-karpenter@1.0.19.jsii.tgz
cdk_eks_karpenter-1.0.19.dist-info/LICENSE
cdk_eks_karpenter-1.0.19.dist-info/METADATA
cdk_eks_karpenter-1.0.19.dist-info/NOTICE
cdk_eks_karpenter-1.0.19.dist-info/WHEEL
cdk_eks_karpenter-1.0.19.dist-info/top_level.txt
cdk_eks_karpenter-1.0.19.dist-info/RECORD
