Metadata-Version: 2.1
Name: cdk-eks-karpenter
Version: 1.0.19
Summary: CDK construct library that allows you install Karpenter in an AWS EKS cluster
Home-page: https://github.com/aws-samples/cdk-eks-karpenter.git
Author: Andreas Lindh<elindh@amazon.com>
License: Apache-2.0
Project-URL: Source, https://github.com/aws-samples/cdk-eks-karpenter.git
Classifier: Intended Audience :: Developers
Classifier: Operating System :: OS Independent
Classifier: Programming Language :: JavaScript
Classifier: Programming Language :: Python :: 3 :: Only
Classifier: Programming Language :: Python :: 3.8
Classifier: Programming Language :: Python :: 3.9
Classifier: Programming Language :: Python :: 3.10
Classifier: Programming Language :: Python :: 3.11
Classifier: Typing :: Typed
Classifier: Development Status :: 5 - Production/Stable
Classifier: License :: OSI Approved
Requires-Python: ~=3.8
License-File: LICENSE
License-File: NOTICE
Requires-Dist: aws-cdk-lib<3.0.0,>=2.178.2
Requires-Dist: constructs<11.0.0,>=10.0.5
Requires-Dist: jsii<2.0.0,>=1.104.0
Requires-Dist: publication>=0.0.3
Requires-Dist: typeguard<4.3.0,>=2.13.3
